ess/__init__.py
ess/ess.py
TOOLS_IDM-2.1.1.dist-info/METADATA
TOOLS_IDM-2.1.1.dist-info/WHEEL
TOOLS_IDM-2.1.1.dist-info/entry_points.txt
TOOLS_IDM-2.1.1.dist-info/top_level.txt
TOOLS_IDM-2.1.1.dist-info/RECORD
